glootalk/__init__.py
glootalk/glootalk.cpython-39-darwin.so
glootalk-0.1.1.dist-info/LICENSE.txt
glootalk-0.1.1.dist-info/METADATA
glootalk-0.1.1.dist-info/WHEEL
glootalk-0.1.1.dist-info/top_level.txt
glootalk-0.1.1.dist-info/RECORD
