Metadata-Version: 2.1
Name: glootalk
Version: 0.1.1
Summary: The glootalk python module.
Home-page: https://github.com/anirrudh/glootalk
Author: Anirrudh Krishnan
Author-email: akrishnan@quansight.com
License: UNKNOWN
Platform: UNKNOWN
